Metadata-Version: 1.1
Name: sewan-drf-tus
Version: 1.2
Summary: A Tus (tus.io) library for Django Rest Framework
Home-page: https://github.com/retenodus/sewan-drf-tus
Author: Gregoire Leroy
Author-email: gregoire.leroy@sewan.fr
License: MIT
Keywords: sewan-drf-tus
Platform: UNKNOWN
Classifier: Development Status :: 3 - Alpha
Classifier: Framework :: Django
Classifier: Framework :: Django :: 1.8
Classifier: Framework :: Django :: 1.9
Classifier: Framework :: Django :: 1.10
Classifier: Framework :: Django :: 1.11
Classifier: Intended Audience :: Developers
Classifier: License :: OSI Approved :: BSD License
Classifier: Natural Language :: English
Classifier: Programming Language :: Python :: 2
Classifier: Programming Language :: Python :: 2.7
Classifier: Programming Language :: Python :: 3
Classifier: Programming Language :: Python :: 3.3
Classifier: Programming Language :: Python :: 3.4
Classifier: Programming Language :: Python :: 3.5
Classifier: Programming Language :: Python :: 3.6
